tiktaknawaf/__init__.py
tiktaknawaf/tiktaknawaf.py
tiktaknawaf-1.0.2.dist-info/LICENSE
tiktaknawaf-1.0.2.dist-info/METADATA
tiktaknawaf-1.0.2.dist-info/WHEEL
tiktaknawaf-1.0.2.dist-info/top_level.txt
tiktaknawaf-1.0.2.dist-info/RECORD
