Metadata-Version: 2.1
Name: tiktaknawaf
Version: 1.0.2
Summary: A powerful TikTok video downloader
Home-page: https://github.com/yourusername/tiktaknawaf
Author: Nawaf
Author-email: your_email@example.com
License: UNKNOWN
Platform: UNKNOWN
Classifier: Programming Language :: Python :: 3
Classifier: License :: OSI Approved :: MIT License
Classifier: Operating System :: OS Independent
Requires-Python: >=3.6
License-File: LICENSE
Requires-Dist: requests
